bapi/__init__.py
bapi/app.py
bapi/api/__init__.py
bapi/api/core.py
bapi/api/price.py
bapi/api/query.py
bapi/api/repo.py
bapi/api/transaction.py
bapi/core/__init__.py
bapi/core/exception.py
bapi/core/storage.py
bapi-0.2.5.dist-info/DESCRIPTION.rst
bapi-0.2.5.dist-info/METADATA
bapi-0.2.5.dist-info/RECORD
bapi-0.2.5.dist-info/WHEEL
bapi-0.2.5.dist-info/entry_points.txt
bapi-0.2.5.dist-info/metadata.json
bapi-0.2.5.dist-info/top_level.txt
tests/core/__init__.py
tests/core/storage_test.py
